brazilian_ids/py.typed
brazilian_ids/functions/exceptions.py
brazilian_ids/functions/util.py
brazilian_ids/functions/company/cnpj.py
brazilian_ids/functions/labor_dispute/nupj.py
brazilian_ids/functions/location/cep.py
brazilian_ids/functions/location/municipio.py
brazilian_ids/functions/location/states.py
brazilian_ids/functions/person/cpf.py
brazilian_ids/functions/person/pis_pasep.py
brazilian_ids/functions/real_state/cno.py
brazilian_ids/functions/real_state/sql.py
brazilian_ids-0.3.0.dist-info/METADATA
brazilian_ids-0.3.0.dist-info/WHEEL
brazilian_ids-0.3.0.dist-info/licenses/LICENSE
brazilian_ids-0.3.0.dist-info/RECORD
