Metadata-Version: 2.3
Name: brazilian_ids
Version: 0.3.0
Summary: provides functions and classes to validate several Brazilian IDs
Project-URL: Homepage, https://github.com/glasswalk3r/brazilian-ids
Project-URL: Repository, https://github.com/glasswalk3r/brazilian-ids.git
Project-URL: Issues, https://github.com/glasswalk3r/brazilian-ids/issues
Author-email: Alceu Rodrigues de Freitas Junior <glasswalk3r@yahoo.com.br>
License:                     GNU GENERAL PUBLIC LICENSE
License-File: LICENSE
Keywords: brasil,brazil,cep,cno,cnpj,cpf,jurídico,municipio,pasep,pis,processo,sql
Classifier: Development Status :: 4 - Beta
Classifier: Intended Audience :: Developers
Classifier: License :: OSI Approved :: GNU General Public License v3 (GPLv3)
Classifier: Operating System :: OS Independent
Classifier: Programming Language :: Python :: 3
Classifier: Programming Language :: Python :: 3.8
Classifier: Programming Language :: Python :: 3.9
Classifier: Programming Language :: Python :: 3.10
Classifier: Programming Language :: Python :: 3.11
Classifier: Programming Language :: Python :: 3.12
Classifier: Programming Language :: Python :: Implementation :: CPython
Classifier: Topic :: Utilities
Requires-Python: >=3.8
